cl_hubeau/__init__.py
cl_hubeau/config.py
cl_hubeau/constants.py
cl_hubeau/drinking_water_quality/__init__.py
cl_hubeau/drinking_water_quality/drinking_water_quality_scraper.py
cl_hubeau/drinking_water_quality/utils.py
cl_hubeau/exceptions.py
cl_hubeau/fish/__init__.py
cl_hubeau/fish/fish_scraper.py
cl_hubeau/fish/utils.py
cl_hubeau/ground_water_quality/__init__.py
cl_hubeau/ground_water_quality/ground_water_quality_scraper.py
cl_hubeau/ground_water_quality/utils.py
cl_hubeau/hydrobiology/__init__.py
cl_hubeau/hydrobiology/hydrobiology_scraper.py
cl_hubeau/hydrobiology/utils.py
cl_hubeau/hydrometry/__init__.py
cl_hubeau/hydrometry/hydrometry_scraper.py
cl_hubeau/hydrometry/utils.py
cl_hubeau/phytopharmaceuticals_transactions/__init__.py
cl_hubeau/phytopharmaceuticals_transactions/phytopharmaceuticals_scraper.py
cl_hubeau/phytopharmaceuticals_transactions/utils.py
cl_hubeau/piezometry/__init__.py
cl_hubeau/piezometry/piezometry_scraper.py
cl_hubeau/piezometry/utils.py
cl_hubeau/session/__init__.py
cl_hubeau/session/session.py
cl_hubeau/superficial_waterbodies_quality/__init__.py
cl_hubeau/superficial_waterbodies_quality/superficial_waterbodies_quality_scraper.py
cl_hubeau/superficial_waterbodies_quality/utils.py
cl_hubeau/utils/__init__.py
cl_hubeau/utils/cities_deps_regions.py
cl_hubeau/utils/clean_cache.py
cl_hubeau/utils/fill_missing_fields.py
cl_hubeau/utils/hydro_perimeters_queries.py
cl_hubeau/utils/mesh.py
cl_hubeau/utils/postcodes.py
cl_hubeau/utils/prepare_loops.py
cl_hubeau/watercourses_flow/__init__.py
cl_hubeau/watercourses_flow/utils.py
cl_hubeau/watercourses_flow/watercourses_flow_scraper.py
cl_hubeau-0.12.0.dist-info/METADATA
cl_hubeau-0.12.0.dist-info/WHEEL
cl_hubeau-0.12.0.dist-info/RECORD
