Metadata-Version: 2.4
Name: cl-hubeau
Version: 0.12.0
Summary: Hubeau client to collect data from the different APIs
License: GPL-3.0-or-later
Keywords: france,water,hydrology
Author: Thomas Grandjean
Author-email: thomas.grandjean@developpement-durable.gouv.fr
Maintainer: Thomas Grandjean
Maintainer-email: thomas.grandjean@developpement-durable.gouv.fr
Requires-Python: >=3.9,<4.0
Classifier: Development Status :: 4 - Beta
Classifier: License :: OSI Approved :: GNU General Public License v3 or later (GPLv3+)
Classifier: Operating System :: OS Independent
Classifier: Programming Language :: Python :: 3
Classifier: Programming Language :: Python :: 3.9
Classifier: Programming Language :: Python :: 3.10
Classifier: Programming Language :: Python :: 3.11
Classifier: Programming Language :: Python :: 3.12
Classifier: Programming Language :: Python :: 3.13
Classifier: Programming Language :: Python :: 3.14
Classifier: Topic :: Scientific/Engineering
Requires-Dist: deprecated (>=1.2.18,<2.0.0)
Requires-Dist: diskcache (>=5.6.3,<6.0.0)
Requires-Dist: french-cities (>=1.1.3,<2.0.0)
Requires-Dist: geopandas (>=1.0.1,<2.0.0)
Requires-Dist: importlib-metadata (>=6.0.0)
Requires-Dist: pandas (>=2.2.2,<3.0.0)
Requires-Dist: pebble (>=5.0.7,<6.0.0)
Requires-Dist: platformdirs (>=4.2.2,<5.0.0)
Requires-Dist: pynsee (>=0.2.3,<0.3.0)
Requires-Dist: requests-cache (>=1.2.1,<2.0.0)
Requires-Dist: requests-ratelimiter (>=0.7.0,<0.8.0)
Requires-Dist: tqdm (>=4.66.4,<5.0.0)
Project-URL: Documentation, https://tgrandje.github.io/cl-hubeau
Project-URL: Homepage, https://tgrandje.github.io/cl-hubeau
Project-URL: Repository, https://github.com/tgrandje/cl-hubeau/
